setup.py
uploadwithus.py
uploadwithus.egg-info/PKG-INFO
uploadwithus.egg-info/SOURCES.txt
uploadwithus.egg-info/dependency_links.txt
uploadwithus.egg-info/entry_points.txt
uploadwithus.egg-info/requires.txt
uploadwithus.egg-info/top_level.txt